{
  "get": {
    "operationId": "getActivities",
    "description": "Get the activites of this widget by Widget Id",
    "parameters": [
      {
        "name": "widgetInstanceId",
        "in": "query",
        "description": "Id of a widget instance",
        "required": true,
        "type": "integer"
      }
    ],
    "responses": {
      "200": {
        "description": "Success"
      },
      "default": {
        "description": "Error",
        "schema": {
          "$ref": "../../definitions/common/errorResponse.json"
        }
      }
    }
  }
}